spotish/__init__.py
spotish/__main__.py
spotish-1.2.5.dist-info/LICENSE.txt
spotish-1.2.5.dist-info/METADATA
spotish-1.2.5.dist-info/WHEEL
spotish-1.2.5.dist-info/entry_points.txt
spotish-1.2.5.dist-info/top_level.txt
spotish-1.2.5.dist-info/RECORD
