Metadata-Version: 2.1
Name: spotish
Version: 1.2.5
Summary: download tracks and playlists on spotify;
Home-page: https://github.com/cykerway/spotish
Author: Cyker Way
Author-email: cykerway@example.com
License: UNKNOWN
Project-URL: Source, https://github.com/cykerway/spotish
Keywords: spotify music
Platform: UNKNOWN
Classifier: Development Status :: 4 - Beta
Classifier: Intended Audience :: End Users/Desktop
Classifier: Topic :: Multimedia
Classifier: License :: OSI Approved :: GNU General Public License v3 (GPLv3)
Classifier: Programming Language :: Python :: 3.6
Classifier: Programming Language :: Python :: 3.7
Requires-Dist: argparse-ext
Requires-Dist: logging-ext
Requires-Dist: spotipy
